[{"FromId":"a9954f60-422f-4ed9-b2e1-53209a9fa422","ToId":"0ea60148-436a-481e-b735-766979a902f7","FromUser":"admin1","ToUser":"admin","HaveMessage":false,"listRM":[{"Message":"eeee","DateCreate":"9/1/2024 1:34:46 AM","DateShow":"9/1/2024, 1:34 AM"},{"Message":"hello","DateCreate":"9/1/2024 1:35:13 AM","DateShow":"9/1/2024, 1:35 AM"},{"Message":"hiiiii","DateCreate":"9/1/2024 1:38:12 AM","DateShow":"9/1/2024, 1:38 AM"},{"Message":"hi","DateCreate":"9/1/2024 1:39:34 AM","DateShow":"9/1/2024, 1:39 AM"},{"Message":"hi","DateCreate":"9/1/2024 1:42:50 AM","DateShow":"9/1/2024, 1:42 AM"}]}]